.gitignore
.gitlab-ci.yml
COPYING.LGPLv3
Makefile
NEWS.txt
README.md
setup.py
src/test_run_simulation_bug.py
src/libresoc_nmutil.egg-info/PKG-INFO
src/libresoc_nmutil.egg-info/SOURCES.txt
src/libresoc_nmutil.egg-info/dependency_links.txt
src/libresoc_nmutil.egg-info/not-zip-safe
src/libresoc_nmutil.egg-info/requires.txt
src/libresoc_nmutil.egg-info/top_level.txt
src/nmutil/__init__.py
src/nmutil/byterev.py
src/nmutil/clz.py
src/nmutil/concurrentunit.py
src/nmutil/divmod.py
src/nmutil/dynamicpipe.py
src/nmutil/extend.py
src/nmutil/formaltest.py
src/nmutil/gtkw.py
src/nmutil/iocontrol.py
src/nmutil/latch.py
src/nmutil/mask.py
src/nmutil/multipipe.py
src/nmutil/nmoperator.py
src/nmutil/noconflict.py
src/nmutil/p_lru.txt
src/nmutil/picker.py
src/nmutil/pipeline.py
src/nmutil/pipemodbase.py
src/nmutil/plru.py
src/nmutil/queue.py
src/nmutil/ripple.py
src/nmutil/sim_tmp_alternative.py
src/nmutil/singlepipe.py
src/nmutil/stageapi.py
src/nmutil/util.py
src/nmutil/formal/proof_clz.py
src/nmutil/test/__init__.py
src/nmutil/test/example_buf_pipe.py
src/nmutil/test/example_gtkwave.py
src/nmutil/test/test_buf_pipe.py
src/nmutil/test/test_clz.py
src/nmutil/test/test_inout_feedback_pipe.py
src/nmutil/test/test_inout_mux_pipe.py
src/nmutil/test/test_inout_unary_mux_cancel_pipe.py
src/nmutil/test/test_outmux_pipe.py
src/nmutil/test/test_prioritymux_pipe.py