Metadata-Version: 1.1
Name: libresoc-nmutil
Version: 0.0.1
Summary: A nmigen utility library
Home-page: http://git.libre-soc.org/?p=nmutil.git
Author: Luke Kenneth Casson Leighton
Author-email: lkcl@libre-soc.org
License: LGPLv3+
Keywords: nmigen utilities
Platform: UNKNOWN
Classifier: Topic :: Software Development :: Libraries
Classifier: License :: OSI Approved :: GNU Lesser General Public License v3 or later (LGPLv3+)
Classifier: Programming Language :: Python :: 3
